XStatic_mdi-1.6.50.2-py3.5-nspkg.pth
xstatic/pkg/mdi/__init__.py
xstatic/pkg/mdi/data/preview.html
xstatic/pkg/mdi/data/css/materialdesignicons.css
xstatic/pkg/mdi/data/css/materialdesignicons.css.map
xstatic/pkg/mdi/data/css/materialdesignicons.min.css
xstatic/pkg/mdi/data/css/materialdesignicons.min.css.map
xstatic/pkg/mdi/data/fonts/materialdesignicons-webfont.eot
xstatic/pkg/mdi/data/fonts/materialdesignicons-webfont.svg
xstatic/pkg/mdi/data/fonts/materialdesignicons-webfont.ttf
xstatic/pkg/mdi/data/fonts/materialdesignicons-webfont.woff
xstatic/pkg/mdi/data/fonts/materialdesignicons-webfont.woff2
xstatic/pkg/mdi/data/scss/_core.scss
xstatic/pkg/mdi/data/scss/_extras.scss
xstatic/pkg/mdi/data/scss/_functions.scss
xstatic/pkg/mdi/data/scss/_icons.scss
xstatic/pkg/mdi/data/scss/_path.scss
xstatic/pkg/mdi/data/scss/_variables.scss
xstatic/pkg/mdi/data/scss/materialdesignicons.scss
XStatic_mdi-1.6.50.2.dist-info/LICENSE
XStatic_mdi-1.6.50.2.dist-info/METADATA
XStatic_mdi-1.6.50.2.dist-info/WHEEL
XStatic_mdi-1.6.50.2.dist-info/namespace_packages.txt
XStatic_mdi-1.6.50.2.dist-info/top_level.txt
XStatic_mdi-1.6.50.2.dist-info/RECORD
