Metadata-Version: 2.1
Name: XStatic-mdi
Version: 1.6.50.2
Summary: mdi 1.6.50 (XStatic packaging standard)
Home-page: http://materialdesignicons.com
Maintainer: Rob Cresswell
Maintainer-email: robert.cresswell@outlook.com
License: SIL OFL 1.1
Keywords: material design icons webfont mdi xstatic
Platform: any
